[
  {
    "id": "bitcoin",
    "symbol": "btc",
    "name": "Bitcoin",
    "image": "https://coin-images.coingecko.com/coins/images/1/large/bitcoin.png?1696501400",
    "current_price": 88864,
    "market_cap": 1776012633396,
    "market_cap_rank": 1,
    "fully_diluted_valuation": 1776012633396,
    "total_volume": 44097135588,
    "high_24h": 89394,
    "low_24h": 87315,
    "price_change_24h": 778.88,
    "price_change_percentage_24h": 0.88424,
    "market_cap_change_24h": 16658961892,
    "market_cap_change_percentage_24h": 0.94688,
    "circulating_supply": 19981446.0,
    "total_supply": 19981446.0,
    "max_supply": 21000000.0,
    "ath": 126080,
    "ath_change_percentage": -29.51748,
    "ath_date": "2025-10-06T18:57:42.558Z",
    "atl": 67.81,
    "atl_change_percentage": 130950.86908,
    "atl_date": "2013-07-06T00:00:00.000Z",
    "roi": null,
    "last_updated": "2026-01-28T08:59:25.380Z"
  },
  {
    "id": "ethereum",
    "symbol": "eth",
    "name": "Ethereum",
    "image": "https://coin-images.coingecko.com/coins/images/279/large/ethereum.png?1696501628",
    "current_price": 2990.3,
    "market_cap": 360976592454,
    "market_cap_rank": 2,
    "fully_diluted_valuation": 360976592454,
    "total_volume": 28449315678,
    "high_24h": 3028.05,
    "low_24h": 2899.35,
    "price_change_24h": 71.47,
    "price_change_percentage_24h": 2.44849,
    "market_cap_change_24h": 8673788818,
    "market_cap_change_percentage_24h": 2.46203,
    "circulating_supply": 120694373.7963051,
    "total_supply": 120694373.7963051,
    "max_supply": null,
    "ath": 4946.05,
    "ath_change_percentage": -39.54162,
    "ath_date": "2025-08-24T19:21:03.333Z",
    "atl": 0.432979,
    "atl_change_percentage": 690534.34378,
    "atl_date": "2015-10-20T00:00:00.000Z",
    "roi": {
      "times": 44.01518475066166,
      "currency": "btc",
      "percentage": 4401.518475066166
    },
    "last_updated": "2026-01-28T08:59:25.573Z"
  },
  {
    "id": "tether",
    "symbol": "usdt",
    "name": "Tether",
    "image": "https://coin-images.coingecko.com/coins/images/325/large/Tether.png?1696501661",
    "current_price": 0.998725,
    "market_cap": 186190201283,
    "market_cap_rank": 3,
    "fully_diluted_valuation": 191650150134,
    "total_volume": 78569783115,
    "high_24h": 0.999892,
    "low_24h": 0.998531,
    "price_change_24h": 3.203e-05,
    "price_change_percentage_24h": 0.00321,
    "market_cap_change_24h": -102125138.8263855,
    "market_cap_change_percentage_24h": -0.05482,
    "circulating_supply": 186428507201.9166,
    "total_supply": 191895444273.2262,
    "max_supply": null,
    "ath": 1.32,
    "ath_change_percentage": -24.51968,
    "ath_date": "2018-07-24T00:00:00.000Z",
    "atl": 0.572521,
    "atl_change_percentage": 74.43492,
    "atl_date": "2015-03-02T00:00:00.000Z",
    "roi": null,
    "last_updated": "2026-01-28T08:59:25.966Z"
  },
  {
    "id": "binancecoin",
    "symbol": "bnb",
    "name": "BNB",
    "image": "https://coin-images.coingecko.com/coins/images/825/large/bnb-icon2_2x.png?1696501970",
    "current_price": 901.35,
    "market_cap": 122925559802,
    "market_cap_rank": 4,
    "fully_diluted_valuation": 122925559802,
    "total_volume": 1367881378,
    "high_24h": 903.46,
    "low_24h": 875.95,
    "price_change_24h": 17.64,
    "price_change_percentage_24h": 1.99605,
    "market_cap_change_24h": 2459029852,
    "market_cap_change_percentage_24h": 2.04126,
    "circulating_supply": 136360308.71,
    "total_supply": 136360308.71,
    "max_supply": 200000000.0,
    "ath": 1369.99,
    "ath_change_percentage": -34.20755,
    "ath_date": "2025-10-13T08:41:24.131Z",
    "atl": 0.0398177,
    "atl_change_percentage": 2263594.51163,
    "atl_date": "2017-10-19T00:00:00.000Z",
    "roi": null,
    "last_updated": "2026-01-28T08:59:25.894Z"
  },
  {
    "id": "ripple",
    "symbol": "xrp",
    "name": "XRP",
    "image": "https://coin-images.coingecko.com/coins/images/44/large/xrp-symbol-white-128.png?1696501442",
    "current_price": 1.91,
    "market_cap": 116120259759,
    "market_cap_rank": 5,
    "fully_diluted_valuation": 190792956259,
    "total_volume": 2156638927,
    "high_24h": 1.92,
    "low_24h": 1.87,
    "price_change_24h": 0.01720229,
    "price_change_percentage_24h": 0.90876,
    "market_cap_change_24h": 963103090,
    "market_cap_change_percentage_24h": 0.83634,
    "circulating_supply": 60853233336.0,
    "total_supply": 99985724371.0,
    "max_supply": 100000000000.0,
    "ath": 3.65,
    "ath_change_percentage": -47.6152,
    "ath_date": "2025-07-18T03:40:53.808Z",
    "atl": 0.00268621,
    "atl_change_percentage": 71009.49052,
    "atl_date": "2014-05-22T00:00:00.000Z",
    "roi": null,
    "last_updated": "2026-01-28T08:59:25.152Z"
  },
  {
    "id": "solana",
    "symbol": "sol",
    "name": "Solana",
    "image": "https://coin-images.coingecko.com/coins/images/4128/large/solana.png?1718769756",
    "current_price": 126.72,
    "market_cap": 71685598195,
    "market_cap_rank": 6,
    "fully_diluted_valuation": 78411196203,
    "total_volume": 3906346020,
    "high_24h": 127.51,
    "low_24h": 123.05,
    "price_change_24h": 2.75,
    "price_change_percentage_24h": 2.22183,
    "market_cap_change_24h": 1510340835,
    "market_cap_change_percentage_24h": 2.15224,
    "circulating_supply": 566068712.7371567,
    "total_supply": 619177715.1356096,
    "max_supply": null,
    "ath": 293.31,
    "ath_change_percentage": -56.79838,
    "ath_date": "2025-01-19T11:15:27.957Z",
    "atl": 0.500801,
    "atl_change_percentage": 25202.55685,
    "atl_date": "2020-05-11T19:35:23.449Z",
    "roi": null,
    "last_updated": "2026-01-28T08:59:22.373Z"
  },
  {
    "id": "usd-coin",
    "symbol": "usdc",
    "name": "USDC",
    "image": "https://coin-images.coingecko.com/coins/images/6319/large/usdc.png?1696506694",
    "current_price": 0.999559,
    "market_cap": 71539280312,
    "market_cap_rank": 7,
    "fully_diluted_valuation": 71528591602,
    "total_volume": 17018597529,
    "high_24h": 0.999752,
    "low_24h": 0.999508,
    "price_change_24h": -4.085947376109e-05,
    "price_change_percentage_24h": -0.00409,
    "market_cap_change_24h": -384468945.31018066,
    "market_cap_change_percentage_24h": -0.53455,
    "circulating_supply": 71569959474.09254,
    "total_supply": 71559266180.20224,
    "max_supply": null,
    "ath": 1.17,
    "ath_change_percentage": -14.76319,
    "ath_date": "2019-05-08T00:40:28.300Z",
    "atl": 0.877647,
    "atl_change_percentage": 13.89291,
    "atl_date": "2023-03-11T08:02:13.981Z",
    "roi": null,
    "last_updated": "2026-01-28T08:59:27.033Z"
  },
  {
    "id": "staked-ether",
    "symbol": "steth",
    "name": "Lido Staked Ether",
    "image": "https://coin-images.coingecko.com/coins/images/13442/large/steth_logo.png?1696513206",
    "current_price": 2994.2,
    "market_cap": 28369163963,
    "market_cap_rank": 8,
    "fully_diluted_valuation": 28369163963,
    "total_volume": 50214360,
    "high_24h": 3028.37,
    "low_24h": 2899.44,
    "price_change_24h": 74.61,
    "price_change_percentage_24h": 2.55541,
    "market_cap_change_24h": 839483990,
    "market_cap_change_percentage_24h": 3.04938,
    "circulating_supply": 9475304.775872918,
    "total_supply": 9475304.775872918,
    "max_supply": null,
    "ath": 4932.89,
    "ath_change_percentage": -39.23765,
    "ath_date": "2025-08-24T19:21:31.902Z",
    "atl": 482.9,
    "atl_change_percentage": 520.70112,
    "atl_date": "2020-12-22T04:08:21.854Z",
    "roi": null,
    "last_updated": "2026-01-28T08:59:23.575Z"
  },
  {
    "id": "tron",
    "symbol": "trx",
    "name": "TRON",
    "image": "https://coin-images.coingecko.com/coins/images/1094/large/tron-logo.png?1696502193",
    "current_price": 0.292286,
    "market_cap": 27686466486,
    "market_cap_rank": 9,
    "fully_diluted_valuation": 27686466631,
    "total_volume": 499027198,
    "high_24h": 0.294652,
    "low_24h": 0.292351,
    "price_change_24h": -0.002091869707491867,
    "price_change_percentage_24h": -0.71061,
    "market_cap_change_24h": -197154203.24380493,
    "market_cap_change_percentage_24h": -0.70706,
    "circulating_supply": 94716651010.87996,
    "total_supply": 94716651505.05707,
    "max_supply": null,
    "ath": 0.431288,
    "ath_change_percentage": -32.22954,
    "ath_date": "2024-12-04T00:10:40.323Z",
    "atl": 0.00180434,
    "atl_change_percentage": 16099.0449,
    "atl_date": "2017-11-12T00:00:00.000Z",
    "roi": {
      "times": 152.834795517542,
      "currency": "usd",
      "percentage": 15283.4795517542
    },
    "last_updated": "2026-01-28T08:59:31.062Z"
  },
  {
    "id": "dogecoin",
    "symbol": "doge",
    "name": "Dogecoin",
    "image": "https://coin-images.coingecko.com/coins/images/5/large/dogecoin.png?1696501409",
    "current_price": 0.125516,
    "market_cap": 21152779233,
    "market_cap_rank": 10,
    "fully_diluted_valuation": 21154843212,
    "total_volume": 1076122009,
    "high_24h": 0.126268,
    "low_24h": 0.121439,
    "price_change_24h": 0.00340792,
    "price_change_percentage_24h": 2.7909,
    "market_cap_change_24h": 577501785,
    "market_cap_change_percentage_24h": 2.80678,
    "circulating_supply": 168486043126.579,
    "total_supply": 168502483126.579,
    "max_supply": null,
    "ath": 0.731578,
    "ath_change_percentage": -82.84313,
    "ath_date": "2021-05-08T05:08:23.458Z",
    "atl": 8.69e-05,
    "atl_change_percentage": 144330.95103,
    "atl_date": "2015-05-06T00:00:00.000Z",
    "roi": null,
    "last_updated": "2026-01-28T08:59:30.709Z"
  },
  {
    "id": "figure-heloc",
    "symbol": "figr_heloc",
    "name": "Figure Heloc",
    "image": "https://coin-images.coingecko.com/coins/images/68480/large/figure.png?1755863954",
    "current_price": 1.035,
    "market_cap": 15354162280,
    "market_cap_rank": 11,
    "fully_diluted_valuation": 15354162280,
    "total_volume": 35723566,
    "high_24h": 1.035,
    "low_24h": 1.03,
    "price_change_24h": 0.0041803,
    "price_change_percentage_24h": 0.40536,
    "market_cap_change_24h": 119767821,
    "market_cap_change_percentage_24h": 0.78617,
    "circulating_supply": 14828837369.937,
    "total_supply": 14828837369.937,
    "max_supply": null,
    "ath": 1.37,
    "ath_change_percentage": -24.39957,
    "ath_date": "2025-10-28T06:05:38.345Z",
    "atl": 0.155357,
    "atl_change_percentage": 566.48337,
    "atl_date": "2025-10-31T14:27:24.456Z",
    "roi": null,
    "last_updated": "2026-01-28T08:59:30.560Z"
  },
  {
    "id": "cardano",
    "symbol": "ada",
    "name": "Cardano",
    "image": "https://coin-images.coingecko.com/coins/images/975/large/cardano.png?1696502090",
    "current_price": 0.357114,
    "market_cap": 13135942136,
    "market_cap_rank": 12,
    "fully_diluted_valuation": 16074282467,
    "total_volume": 482166441,
    "high_24h": 0.361728,
    "low_24h": 0.34784,
    "price_change_24h": 0.0058211,
    "price_change_percentage_24h": 1.65705,
    "market_cap_change_24h": 216473649,
    "market_cap_change_percentage_24h": 1.67556,
    "circulating_supply": 36774107790.58057,
    "total_supply": 45000000000.0,
    "max_supply": 45000000000.0,
    "ath": 3.09,
    "ath_change_percentage": -88.43135,
    "ath_date": "2021-09-02T06:00:10.474Z",
    "atl": 0.01925275,
    "atl_change_percentage": 1754.87234,
    "atl_date": "2020-03-13T02:22:55.044Z",
    "roi": null,
    "last_updated": "2026-01-28T08:59:27.664Z"
  },
  {
    "id": "wrapped-steth",
    "symbol": "wsteth",
    "name": "Wrapped stETH",
    "image": "https://coin-images.coingecko.com/coins/images/18834/large/wstETH.png?1696518295",
    "current_price": 3673.63,
    "market_cap": 12661178592,
    "market_cap_rank": 13,
    "fully_diluted_valuation": 12662148328,
    "total_volume": 103454534,
    "high_24h": 3712.28,
    "low_24h": 3552.41,
    "price_change_24h": 98.62,
    "price_change_percentage_24h": 2.75857,
    "market_cap_change_24h": 366231622,
    "market_cap_change_percentage_24h": 2.97872,
    "circulating_supply": 3447145.238470791,
    "total_supply": 3447409.259658624,
    "max_supply": null,
    "ath": 7256.02,
    "ath_change_percentage": -49.29405,
    "ath_date": "2022-05-13T15:09:54.509Z",
    "atl": 558.54,
    "atl_change_percentage": 558.72339,
    "atl_date": "2022-05-13T01:36:45.053Z",
    "roi": null,
    "last_updated": "2026-01-28T08:59:26.903Z"
  },
  {
    "id": "bitcoin-cash",
    "symbol": "bch",
    "name": "Bitcoin Cash",
    "image": "https://coin-images.coingecko.com/coins/images/780/large/bitcoin-cash-circle.png?1696501932",
    "current_price": 591.85,
    "market_cap": 11828927065,
    "market_cap_rank": 14,
    "fully_diluted_valuation": 11829147155,
    "total_volume": 312826521,
    "high_24h": 602.0,
    "low_24h": 585.74,
    "price_change_24h": 3.61,
    "price_change_percentage_24h": 0.6141,
    "market_cap_change_24h": 68957817,
    "market_cap_change_percentage_24h": 0.58638,
    "circulating_supply": 19986759.27165078,
    "total_supply": 19987131.14665078,
    "max_supply": 21000000.0,
    "ath": 3785.82,
    "ath_change_percentage": -84.36654,
    "ath_date": "2017-12-20T00:00:00.000Z",
    "atl": 76.93,
    "atl_change_percentage": 669.29399,
    "atl_date": "2018-12-16T00:00:00.000Z",
    "roi": null,
    "last_updated": "2026-01-28T08:59:30.243Z"
  },
  {
    "id": "whitebit",
    "symbol": "wbt",
    "name": "WhiteBIT Coin",
    "image": "https://coin-images.coingecko.com/coins/images/27045/large/wbt_token.png?1696526096",
    "current_price": 54.35,
    "market_cap": 11623806639,
    "market_cap_rank": 15,
    "fully_diluted_valuation": 17412391582,
    "total_volume": 50031334,
    "high_24h": 54.71,
    "low_24h": 53.34,
    "price_change_24h": 0.567581,
    "price_change_percentage_24h": 1.05527,
    "market_cap_change_24h": 121786483,
    "market_cap_change_percentage_24h": 1.05883,
    "circulating_supply": 213858036.0,
    "total_supply": 320358036.0,
    "max_supply": 400000000.0,
    "ath": 64.11,
    "ath_change_percentage": -15.18998,
    "ath_date": "2025-12-10T20:16:13.582Z",
    "atl": 3.06,
    "atl_change_percentage": 1675.75202,
    "atl_date": "2023-02-13T19:01:21.899Z",
    "roi": null,
    "last_updated": "2026-01-28T08:59:26.799Z"
  },
  {
    "id": "wrapped-bitcoin",
    "symbol": "wbtc",
    "name": "Wrapped Bitcoin",
    "image": "https://coin-images.coingecko.com/coins/images/7598/large/WBTCLOGO.png?1764496367",
    "current_price": 88781,
    "market_cap": 11105983790,
    "market_cap_rank": 16,
    "fully_diluted_valuation": 11105983790,
    "total_volume": 159172112,
    "high_24h": 89216,
    "low_24h": 86995,
    "price_change_24h": 806.89,
    "price_change_percentage_24h": 0.91719,
    "market_cap_change_24h": 112307238,
    "market_cap_change_percentage_24h": 1.02156,
    "circulating_supply": 124963.48883569,
    "total_supply": 124963.48883569,
    "max_supply": null,
    "ath": 125932,
    "ath_change_percentage": -29.30845,
    "ath_date": "2025-10-06T18:55:19.650Z",
    "atl": 3139.17,
    "atl_change_percentage": 2735.88192,
    "atl_date": "2019-04-02T00:00:00.000Z",
    "roi": null,
    "last_updated": "2026-01-28T08:59:23.053Z"
  },
  {
    "id": "wrapped-beacon-eth",
    "symbol": "wbeth",
    "name": "Wrapped Beacon ETH",
    "image": "https://coin-images.coingecko.com/coins/images/30061/large/wbeth-icon.png?1696528983",
    "current_price": 3264.8,
    "market_cap": 10982284821,
    "market_cap_rank": 17,
    "fully_diluted_valuation": 10982284821,
    "total_volume": 2002247,
    "high_24h": 3298.2,
    "low_24h": 3156.99,
    "price_change_24h": 83.98,
    "price_change_percentage_24h": 2.64013,
    "market_cap_change_24h": 284298486,
    "market_cap_change_percentage_24h": 2.6575,
    "circulating_supply": 3364747.005027684,
    "total_supply": 3364747.005041794,
    "max_supply": null,
    "ath": 5330.78,
    "ath_change_percentage": -38.57432,
    "ath_date": "2025-08-24T19:27:46.809Z",
    "atl": 1501.6,
    "atl_change_percentage": 118.06511,
    "atl_date": "2025-04-09T03:57:40.245Z",
    "roi": null,
    "last_updated": "2026-01-28T08:59:25.782Z"
  },
  {
    "id": "wrapped-eeth",
    "symbol": "weeth",
    "name": "Wrapped eETH",
    "image": "https://coin-images.coingecko.com/coins/images/33033/large/weETH.png?1701438396",
    "current_price": 3256.43,
    "market_cap": 9868567573,
    "market_cap_rank": 18,
    "fully_diluted_valuation": 9868564875,
    "total_volume": 51326255,
    "high_24h": 3293.18,
    "low_24h": 3149.52,
    "price_change_24h": 86.52,
    "price_change_percentage_24h": 2.72932,
    "market_cap_change_24h": 308000077,
    "market_cap_change_percentage_24h": 3.22157,
    "circulating_supply": 3030470.171497542,
    "total_supply": 3030469.342950432,
    "max_supply": null,
    "ath": 5296.78,
    "ath_change_percentage": -38.41922,
    "ath_date": "2025-08-24T19:25:19.771Z",
    "atl": 1505.24,
    "atl_change_percentage": 116.69696,
    "atl_date": "2025-04-09T03:45:31.391Z",
    "roi": null,
    "last_updated": "2026-01-28T08:59:26.844Z"
  },
  {
    "id": "usds",
    "symbol": "usds",
    "name": "USDS",
    "image": "https://coin-images.coingecko.com/coins/images/39926/large/usds.webp?1726666683",
    "current_price": 0.999428,
    "market_cap": 9262418060,
    "market_cap_rank": 19,
    "fully_diluted_valuation": 9262418060,
    "total_volume": 3207991,
    "high_24h": 1.001,
    "low_24h": 0.996504,
    "price_change_24h": -9.8692998238503e-05,
    "price_change_percentage_24h": -0.00987,
    "market_cap_change_24h": 16188250,
    "market_cap_change_percentage_24h": 0.17508,
    "circulating_supply": 9267130250.556406,
    "total_supply": 9267130250.556406,
    "max_supply": null,
    "ath": 1.057,
    "ath_change_percentage": -5.47699,
    "ath_date": "2024-10-29T05:40:51.197Z",
    "atl": 0.948265,
    "atl_change_percentage": 5.3938,
    "atl_date": "2024-10-03T13:19:28.826Z",
    "roi": null,
    "last_updated": "2026-01-28T08:59:26.587Z"
  },
  {
    "id": "binance-bridged-usdt-bnb-smart-chain",
    "symbol": "bsc-usd",
    "name": "Binance Bridged USDT (BNB Smart Chain)",
    "image": "https://coin-images.coingecko.com/coins/images/35021/large/USDT.png?1707233575",
    "current_price": 0.999373,
    "market_cap": 8974793953,
    "market_cap_rank": 20,
    "fully_diluted_valuation": 8974793953,
    "total_volume": 1333202790,
    "high_24h": 0.999709,
    "low_24h": 0.99816,
    "price_change_24h": 0.00082083,
    "price_change_percentage_24h": 0.0822,
    "market_cap_change_24h": 1642923,
    "market_cap_change_percentage_24h": 0.01831,
    "circulating_supply": 8984992789.453934,
    "total_supply": 8984992789.453934,
    "max_supply": null,
    "ath": 1.05,
    "ath_change_percentage": -4.8899,
    "ath_date": "2024-08-05T14:21:42.527Z",
    "atl": 0.942186,
    "atl_change_percentage": 5.98959,
    "atl_date": "2024-12-05T22:30:39.827Z",
    "roi": null,
    "last_updated": "2026-01-28T08:59:30.628Z"
  },
  {
    "id": "monero",
    "symbol": "xmr",
    "name": "Monero",
    "image": "https://coin-images.coingecko.com/coins/images/69/large/monero_logo.png?1696501460",
    "current_price": 473.69,
    "market_cap": 8744022393,
    "market_cap_rank": 21,
    "fully_diluted_valuation": 8744022393,
    "total_volume": 133235340,
    "high_24h": 483.03,
    "low_24h": 456.49,
    "price_change_24h": 1.67,
    "price_change_percentage_24h": 0.35354,
    "market_cap_change_24h": 27436565,
    "market_cap_change_percentage_24h": 0.31476,
    "circulating_supply": 18446744.07370955,
    "total_supply": 18446744.07370955,
    "max_supply": null,
    "ath": 797.73,
    "ath_change_percentage": -40.62094,
    "ath_date": "2026-01-14T19:34:07.049Z",
    "atl": 0.216177,
    "atl_change_percentage": 219020.49685,
    "atl_date": "2015-01-14T00:00:00.000Z",
    "roi": null,
    "last_updated": "2026-01-28T08:59:31.643Z"
  },
  {
    "id": "leo-token",
    "symbol": "leo",
    "name": "LEO Token",
    "image": "https://coin-images.coingecko.com/coins/images/8418/large/leo-token.png?1696508607",
    "current_price": 9.16,
    "market_cap": 8438450226,
    "market_cap_rank": 22,
    "fully_diluted_valuation": 9020240955,
    "total_volume": 2166378,
    "high_24h": 9.27,
    "low_24h": 9.05,
    "price_change_24h": -0.07354893943049845,
    "price_change_percentage_24h": -0.79691,
    "market_cap_change_24h": -69818976.42729759,
    "market_cap_change_percentage_24h": -0.8206,
    "circulating_supply": 921693173.9,
    "total_supply": 985239504.0,
    "max_supply": null,
    "ath": 10.14,
    "ath_change_percentage": -9.68232,
    "ath_date": "2025-03-10T09:26:43.294Z",
    "atl": 0.799859,
    "atl_change_percentage": 1044.42587,
    "atl_date": "2019-12-24T15:14:35.376Z",
    "roi": null,
    "last_updated": "2026-01-28T08:59:31.256Z"
  },
  {
    "id": "chainlink",
    "symbol": "link",
    "name": "Chainlink",
    "image": "https://coin-images.coingecko.com/coins/images/877/large/Chainlink_Logo_500.png?1760023405",
    "current_price": 11.91,
    "market_cap": 8435013814,
    "market_cap_rank": 23,
    "fully_diluted_valuation": 11912179306,
    "total_volume": 378792325,
    "high_24h": 12.15,
    "low_24h": 11.84,
    "price_change_24h": -0.03303446350667727,
    "price_change_percentage_24h": -0.27657,
    "market_cap_change_24h": -24533241.30681324,
    "market_cap_change_percentage_24h": -0.29001,
    "circulating_supply": 708099970.4525867,
    "total_supply": 1000000000.0,
    "max_supply": 1000000000.0,
    "ath": 52.7,
    "ath_change_percentage": -77.39614,
    "ath_date": "2021-05-10T00:13:57.214Z",
    "atl": 0.148183,
    "atl_change_percentage": 7938.33935,
    "atl_date": "2017-11-29T00:00:00.000Z",
    "roi": null,
    "last_updated": "2026-01-28T08:59:30.659Z"
  },
  {
    "id": "hyperliquid",
    "symbol": "hype",
    "name": "Hyperliquid",
    "image": "https://coin-images.coingecko.com/coins/images/50882/large/hyperliquid.jpg?1729431300",
    "current_price": 33.64,
    "market_cap": 8015384353,
    "market_cap_rank": 24,
    "fully_diluted_valuation": 32355164848,
    "total_volume": 871018667,
    "high_24h": 34.4,
    "low_24h": 27.24,
    "price_change_24h": 5.65,
    "price_change_percentage_24h": 20.18426,
    "market_cap_change_24h": 1365770148,
    "market_cap_change_percentage_24h": 20.53909,
    "circulating_supply": 238385315.9541414,
    "total_supply": 962274028.9541414,
    "max_supply": 1000000000.0,
    "ath": 59.3,
    "ath_change_percentage": -43.27739,
    "ath_date": "2025-09-18T03:30:30.650Z",
    "atl": 3.81,
    "atl_change_percentage": 783.19436,
    "atl_date": "2024-11-29T09:30:30.871Z",
    "roi": null,
    "last_updated": "2026-01-28T08:59:29.044Z"
  },
  {
    "id": "coinbase-wrapped-btc",
    "symbol": "cbbtc",
    "name": "Coinbase Wrapped BTC",
    "image": "https://coin-images.coingecko.com/coins/images/40143/large/cbbtc.webp?1726136727",
    "current_price": 89004,
    "market_cap": 7057900520,
    "market_cap_rank": 25,
    "fully_diluted_valuation": 7057900520,
    "total_volume": 328117129,
    "high_24h": 89389,
    "low_24h": 87302,
    "price_change_24h": 932.33,
    "price_change_percentage_24h": 1.0586,
    "market_cap_change_24h": 114043928,
    "market_cap_change_percentage_24h": 1.64237,
    "circulating_supply": 79212.62084363,
    "total_supply": 79212.62084363,
    "max_supply": null,
    "ath": 125954,
    "ath_change_percentage": -29.21938,
    "ath_date": "2025-10-06T18:58:50.734Z",
    "atl": 57439,
    "atl_change_percentage": 55.21032,
    "atl_date": "2024-09-12T14:07:41.775Z",
    "roi": null,
    "last_updated": "2026-01-28T08:59:33.337Z"
  },
  {
    "id": "weth",
    "symbol": "weth",
    "name": "WETH",
    "image": "https://coin-images.coingecko.com/coins/images/2518/large/weth.png?1696503332",
    "current_price": 2997.62,
    "market_cap": 6849591182,
    "market_cap_rank": 26,
    "fully_diluted_valuation": 6849591182,
    "total_volume": 167272854,
    "high_24h": 3030.12,
    "low_24h": 2899.54,
    "price_change_24h": 77.37,
    "price_change_percentage_24h": 2.64936,
    "market_cap_change_24h": -1850480.991326332,
    "market_cap_change_percentage_24h": -0.02701,
    "circulating_supply": 2285071.086119393,
    "total_supply": 2285071.086119393,
    "max_supply": null,
    "ath": 4950.08,
    "ath_change_percentage": -39.34762,
    "ath_date": "2025-08-24T19:28:11.411Z",
    "atl": 82.1,
    "atl_change_percentage": 3556.77836,
    "atl_date": "2018-12-15T00:00:00.000Z",
    "roi": null,
    "last_updated": "2026-01-28T08:59:57.982Z"
  },
  {
    "id": "stellar",
    "symbol": "xlm",
    "name": "Stellar",
    "image": "https://coin-images.coingecko.com/coins/images/100/large/fmpFRHHQ_400x400.jpg?1735231350",
    "current_price": 0.208843,
    "market_cap": 6772256400,
    "market_cap_rank": 27,
    "fully_diluted_valuation": 10442579941,
    "total_volume": 113649616,
    "high_24h": 0.209613,
    "low_24h": 0.203453,
    "price_change_24h": 0.00289932,
    "price_change_percentage_24h": 1.40782,
    "market_cap_change_24h": 94151097,
    "market_cap_change_percentage_24h": 1.40985,
    "circulating_supply": 32427323818.77948,
    "total_supply": 50001786883.65895,
    "max_supply": null,
    "ath": 0.875563,
    "ath_change_percentage": -76.14127,
    "ath_date": "2018-01-03T00:00:00.000Z",
    "atl": 0.00047612,
    "atl_change_percentage": 43774.80551,
    "atl_date": "2015-03-05T00:00:00.000Z",
    "roi": null,
    "last_updated": "2026-01-28T08:59:59.806Z"
  },
  {
    "id": "ethena-usde",
    "symbol": "usde",
    "name": "Ethena USDe",
    "image": "https://coin-images.coingecko.com/coins/images/33613/large/usde.png?1733810059",
    "current_price": 0.999615,
    "market_cap": 6594213279,
    "market_cap_rank": 28,
    "fully_diluted_valuation": 6594213279,
    "total_volume": 98642653,
    "high_24h": 1.001,
    "low_24h": 0.9979,
    "price_change_24h": 0.00088575,
    "price_change_percentage_24h": 0.08869,
    "market_cap_change_24h": 5141762,
    "market_cap_change_percentage_24h": 0.07803,
    "circulating_supply": 6596761908.869284,
    "total_supply": 6596761908.869284,
    "max_supply": null,
    "ath": 1.034,
    "ath_change_percentage": -3.24873,
    "ath_date": "2025-12-09T17:10:12.652Z",
    "atl": 0.929486,
    "atl_change_percentage": 7.63273,
    "atl_date": "2024-10-04T07:57:15.809Z",
    "roi": null,
    "last_updated": "2026-01-28T09:00:06.237Z"
  },
  {
    "id": "zcash",
    "symbol": "zec",
    "name": "Zcash",
    "image": "https://coin-images.coingecko.com/coins/images/486/large/circle-zcash-color.png?1696501740",
    "current_price": 390.67,
    "market_cap": 6462716664,
    "market_cap_rank": 29,
    "fully_diluted_valuation": 6462716664,
    "total_volume": 382622602,
    "high_24h": 401.94,
    "low_24h": 376.77,
    "price_change_24h": 12.75,
    "price_change_percentage_24h": 3.37351,
    "market_cap_change_24h": 222567345,
    "market_cap_change_percentage_24h": 3.5667,
    "circulating_supply": 16511426.7280448,
    "total_supply": 16511426.7280448,
    "max_supply": 21000000.0,
    "ath": 3191.93,
    "ath_change_percentage": -87.76077,
    "ath_date": "2016-10-29T00:00:00.000Z",
    "atl": 16.08,
    "atl_change_percentage": 2329.50562,
    "atl_date": "2024-07-05T04:22:29.321Z",
    "roi": null,
    "last_updated": "2026-01-28T09:00:05.897Z"
  },
  {
    "id": "canton-network",
    "symbol": "cc",
    "name": "Canton",
    "image": "https://coin-images.coingecko.com/coins/images/70468/large/Canton-Ticker_%281%29.png?1762826299",
    "current_price": 0.163242,
    "market_cap": 6138224221,
    "market_cap_rank": 30,
    "fully_diluted_valuation": 6138224221,
    "total_volume": 17129904,
    "high_24h": 0.163331,
    "low_24h": 0.147423,
    "price_change_24h": 0.00835343,
    "price_change_percentage_24h": 5.39318,
    "market_cap_change_24h": 321603048,
    "market_cap_change_percentage_24h": 5.52904,
    "circulating_supply": 37565345848.42798,
    "total_supply": 37565345848.42798,
    "max_supply": null,
    "ath": 0.176091,
    "ath_change_percentage": -7.92932,
    "ath_date": "2026-01-01T13:30:26.939Z",
    "atl": 0.059024,
    "atl_change_percentage": 174.68108,
    "atl_date": "2025-12-06T10:32:09.784Z",
    "roi": null,
    "last_updated": "2026-01-28T09:00:04.505Z"
  },
  {
    "id": "sui",
    "symbol": "sui",
    "name": "Sui",
    "image": "https://coin-images.coingecko.com/coins/images/26375/large/sui-ocean-square.png?1727791290",
    "current_price": 1.42,
    "market_cap": 5399306160,
    "market_cap_rank": 31,
    "fully_diluted_valuation": 14237989183,
    "total_volume": 590040566,
    "high_24h": 1.46,
    "low_24h": 1.42,
    "price_change_24h": -0.015520243339284034,
    "price_change_percentage_24h": -1.07841,
    "market_cap_change_24h": -59294138.18926239,
    "market_cap_change_percentage_24h": -1.08625,
    "circulating_supply": 3792183074.773887,
    "total_supply": 10000000000.0,
    "max_supply": 10000000000.0,
    "ath": 5.35,
    "ath_change_percentage": -73.37248,
    "ath_date": "2025-01-04T22:56:18.063Z",
    "atl": 0.364846,
    "atl_change_percentage": 290.20766,
    "atl_date": "2023-10-19T10:40:30.078Z",
    "roi": null,
    "last_updated": "2026-01-28T08:59:57.376Z"
  },
  {
    "id": "litecoin",
    "symbol": "ltc",
    "name": "Litecoin",
    "image": "https://coin-images.coingecko.com/coins/images/2/large/litecoin.png?1696501400",
    "current_price": 69.42,
    "market_cap": 5330548675,
    "market_cap_rank": 32,
    "fully_diluted_valuation": 5330582953,
    "total_volume": 355402781,
    "high_24h": 70.18,
    "low_24h": 68.6,
    "price_change_24h": 0.106402,
    "price_change_percentage_24h": 0.15352,
    "market_cap_change_24h": 8059812,
    "market_cap_change_percentage_24h": 0.15143,
    "circulating_supply": 76783495.73347135,
    "total_supply": 76783989.48347135,
    "max_supply": 84000000.0,
    "ath": 410.26,
    "ath_change_percentage": -83.05898,
    "ath_date": "2021-05-10T03:13:07.904Z",
    "atl": 1.15,
    "atl_change_percentage": 5949.75772,
    "atl_date": "2015-01-14T00:00:00.000Z",
    "roi": null,
    "last_updated": "2026-01-28T08:59:56.220Z"
  },
  {
    "id": "avalanche-2",
    "symbol": "avax",
    "name": "Avalanche",
    "image": "https://coin-images.coingecko.com/coins/images/12559/large/Avalanche_Circle_RedWhite_Trans.png?1696512369",
    "current_price": 12.05,
    "market_cap": 5197737032,
    "market_cap_rank": 33,
    "fully_diluted_valuation": 5579389088,
    "total_volume": 295997152,
    "high_24h": 12.14,
    "low_24h": 11.59,
    "price_change_24h": 0.300039,
    "price_change_percentage_24h": 2.55368,
    "market_cap_change_24h": 129268853,
    "market_cap_change_percentage_24h": 2.55045,
    "circulating_supply": 431302652.2710733,
    "total_supply": 462971731.0786803,
    "max_supply": 720000000.0,
    "ath": 144.96,
    "ath_change_percentage": -91.68905,
    "ath_date": "2021-11-21T14:18:56.538Z",
    "atl": 2.8,
    "atl_change_percentage": 330.1099,
    "atl_date": "2020-12-31T13:15:21.540Z",
    "roi": null,
    "last_updated": "2026-01-28T09:00:05.766Z"
  },
  {
    "id": "usd1-wlfi",
    "symbol": "usd1",
    "name": "USD1",
    "image": "https://coin-images.coingecko.com/coins/images/54977/large/USD1_1000x1000_transparent.png?1749297002",
    "current_price": 0.999962,
    "market_cap": 4959770343,
    "market_cap_rank": 34,
    "fully_diluted_valuation": 4959770343,
    "total_volume": 867768501,
    "high_24h": 1.0,
    "low_24h": 0.999144,
    "price_change_24h": 0.0003556,
    "price_change_percentage_24h": 0.03557,
    "market_cap_change_24h": 15647281,
    "market_cap_change_percentage_24h": 0.31648,
    "circulating_supply": 4960617881.437494,
    "total_supply": 4960617881.437494,
    "max_supply": null,
    "ath": 1.025,
    "ath_change_percentage": -2.49221,
    "ath_date": "2025-05-12T12:36:39.412Z",
    "atl": 0.989633,
    "atl_change_percentage": 0.97536,
    "atl_date": "2025-10-01T08:51:32.103Z",
    "roi": null,
    "last_updated": "2026-01-28T08:59:57.639Z"
  },
  {
    "id": "hedera-hashgraph",
    "symbol": "hbar",
    "name": "Hedera",
    "image": "https://coin-images.coingecko.com/coins/images/3688/large/hbar.png?1696504364",
    "current_price": 0.107213,
    "market_cap": 4588194703,
    "market_cap_rank": 35,
    "fully_diluted_valuation": 5360745225,
    "total_volume": 88625335,
    "high_24h": 0.108331,
    "low_24h": 0.104671,
    "price_change_24h": 0.00104148,
    "price_change_percentage_24h": 0.98094,
    "market_cap_change_24h": 45202381,
    "market_cap_change_percentage_24h": 0.99499,
    "circulating_supply": 42794373832.61594,
    "total_supply": 50000000000.0,
    "max_supply": 50000000000.0,
    "ath": 0.569229,
    "ath_change_percentage": -81.12873,
    "ath_date": "2021-09-15T10:40:28.318Z",
    "atl": 0.00986111,
    "atl_change_percentage": 989.33706,
    "atl_date": "2020-01-02T17:30:24.852Z",
    "roi": null,
    "last_updated": "2026-01-28T09:00:04.636Z"
  },
  {
    "id": "shiba-inu",
    "symbol": "shib",
    "name": "Shiba Inu",
    "image": "https://coin-images.coingecko.com/coins/images/11939/large/shiba.png?1696511800",
    "current_price": 7.73e-06,
    "market_cap": 4557158023,
    "market_cap_rank": 36,
    "fully_diluted_valuation": 4559141999,
    "total_volume": 100146172,
    "high_24h": 7.87e-06,
    "low_24h": 7.62e-06,
    "price_change_24h": 8.2227e-08,
    "price_change_percentage_24h": 1.07457,
    "market_cap_change_24h": 47672612,
    "market_cap_change_percentage_24h": 1.05716,
    "circulating_supply": 589243926165765.6,
    "total_supply": 589500455768069.8,
    "max_supply": null,
    "ath": 8.616e-05,
    "ath_change_percentage": -91.02322,
    "ath_date": "2021-10-28T03:54:55.568Z",
    "atl": 5.6366e-11,
    "atl_change_percentage": 13721350.18231,
    "atl_date": "2020-11-28T11:26:25.838Z",
    "roi": null,
    "last_updated": "2026-01-28T08:59:59.543Z"
  },
  {
    "id": "world-liberty-financial",
    "symbol": "wlfi",
    "name": "World Liberty Financial",
    "image": "https://coin-images.coingecko.com/coins/images/50767/large/wlfi.png?1756438915",
    "current_price": 0.16406,
    "market_cap": 4472382363,
    "market_cap_rank": 37,
    "fully_diluted_valuation": 16416145860,
    "total_volume": 100758391,
    "high_24h": 0.167578,
    "low_24h": 0.15619,
    "price_change_24h": 0.00591626,
    "price_change_percentage_24h": 3.74107,
    "market_cap_change_24h": 163948921,
    "market_cap_change_percentage_24h": 3.8053,
    "circulating_supply": 27243802538.151154,
    "total_supply": 100000000000.0,
    "max_supply": 100000000000.0,
    "ath": 0.331336,
    "ath_change_percentage": -50.48533,
    "ath_date": "2025-09-01T12:20:09.597Z",
    "atl": 0.104606,
    "atl_change_percentage": 56.83642,
    "atl_date": "2025-10-10T21:22:29.880Z",
    "roi": null,
    "last_updated": "2026-01-28T09:00:00.132Z"
  },
  {
    "id": "usdt0",
    "symbol": "usdt0",
    "name": "USDT0",
    "image": "https://coin-images.coingecko.com/coins/images/53705/large/usdt0.jpg?1737086183",
    "current_price": 0.998409,
    "market_cap": 4432872942,
    "market_cap_rank": 38,
    "fully_diluted_valuation": 4432872942,
    "total_volume": 170120558,
    "high_24h": 1.0,
    "low_24h": 0.997654,
    "price_change_24h": -0.00012945086172067,
    "price_change_percentage_24h": -0.01296,
    "market_cap_change_24h": -193270291.08500195,
    "market_cap_change_percentage_24h": -4.17778,
    "circulating_supply": 4439858285.3482,
    "total_supply": 4439858285.3482,
    "max_supply": null,
    "ath": 1.052,
    "ath_change_percentage": -5.10073,
    "ath_date": "2025-01-23T22:34:53.341Z",
    "atl": 0.975737,
    "atl_change_percentage": 2.32022,
    "atl_date": "2025-02-28T01:35:58.101Z",
    "roi": null,
    "last_updated": "2026-01-28T09:00:00.439Z"
  },
  {
    "id": "dai",
    "symbol": "dai",
    "name": "Dai",
    "image": "https://coin-images.coingecko.com/coins/images/9956/large/Badge_Dai.png?1696509996",
    "current_price": 0.999133,
    "market_cap": 4351232626,
    "market_cap_rank": 39,
    "fully_diluted_valuation": 4351232626,
    "total_volume": 58634195,
    "high_24h": 1.001,
    "low_24h": 0.997649,
    "price_change_24h": -0.000543646469707171,
    "price_change_percentage_24h": -0.05438,
    "market_cap_change_24h": -16666526.597179413,
    "market_cap_change_percentage_24h": -0.38157,
    "circulating_supply": 4354995565.646798,
    "total_supply": 4354995565.646798,
    "max_supply": null,
    "ath": 1.22,
    "ath_change_percentage": -17.98304,
    "ath_date": "2020-03-13T03:02:50.373Z",
    "atl": 0.88196,
    "atl_change_percentage": 13.3532,
    "atl_date": "2023-03-11T07:50:50.514Z",
    "roi": null,
    "last_updated": "2026-01-28T09:00:02.648Z"
  },
  {
    "id": "susds",
    "symbol": "susds",
    "name": "sUSDS",
    "image": "https://coin-images.coingecko.com/coins/images/52721/large/sUSDS_Coin.png?1734086971",
    "current_price": 1.088,
    "market_cap": 4264906114,
    "market_cap_rank": 40,
    "fully_diluted_valuation": 4264906114,
    "total_volume": 9631163,
    "high_24h": 1.09,
    "low_24h": 1.078,
    "price_change_24h": 0.004655,
    "price_change_percentage_24h": 0.42966,
    "market_cap_change_24h": 80667670,
    "market_cap_change_percentage_24h": 1.92789,
    "circulating_supply": 3916749418.9146,
    "total_supply": 3916749418.9146,
    "max_supply": null,
    "ath": 1.11,
    "ath_change_percentage": -1.40676,
    "ath_date": "2025-10-10T21:52:27.019Z",
    "atl": 0.961716,
    "atl_change_percentage": 13.28953,
    "atl_date": "2025-01-04T01:21:08.460Z",
    "roi": null,
    "last_updated": "2026-01-28T08:59:57.047Z"
  },
  {
    "id": "paypal-usd",
    "symbol": "pyusd",
    "name": "PayPal USD",
    "image": "https://coin-images.coingecko.com/coins/images/31212/large/PYUSD_Token_Logo_2x.png?1765987788",
    "current_price": 0.999798,
    "market_cap": 3822728825,
    "market_cap_rank": 41,
    "fully_diluted_valuation": 3822728825,
    "total_volume": 102694776,
    "high_24h": 1.001,
    "low_24h": 0.998271,
    "price_change_24h": 0.00109898,
    "price_change_percentage_24h": 0.11004,
    "market_cap_change_24h": -32428255.510393143,
    "market_cap_change_percentage_24h": -0.84117,
    "circulating_supply": 3823729996.772994,
    "total_supply": 3823729996.781515,
    "max_supply": null,
    "ath": 1.021,
    "ath_change_percentage": -2.07248,
    "ath_date": "2023-10-23T22:44:57.056Z",
    "atl": 0.959426,
    "atl_change_percentage": 4.18549,
    "atl_date": "2024-12-05T22:31:13.430Z",
    "roi": null,
    "last_updated": "2026-01-28T09:00:05.658Z"
  },
  {
    "id": "ethena-staked-usde",
    "symbol": "susde",
    "name": "Ethena Staked USDe",
    "image": "https://coin-images.coingecko.com/coins/images/33669/large/sUSDe-Symbol-Color.png?1716307680",
    "current_price": 1.22,
    "market_cap": 3799400312,
    "market_cap_rank": 42,
    "fully_diluted_valuation": 3799400312,
    "total_volume": 20797946,
    "high_24h": 1.22,
    "low_24h": 1.22,
    "price_change_24h": -0.000546566423460959,
    "price_change_percentage_24h": -0.04494,
    "market_cap_change_24h": 2434026,
    "market_cap_change_percentage_24h": 0.0641,
    "circulating_supply": 3125165014.078768,
    "total_supply": 3125165014.078768,
    "max_supply": null,
    "ath": 1.29,
    "ath_change_percentage": -5.80051,
    "ath_date": "2025-01-29T17:52:32.991Z",
    "atl": 1.012,
    "atl_change_percentage": 20.12992,
    "atl_date": "2024-04-03T14:23:03.162Z",
    "roi": null,
    "last_updated": "2026-01-28T09:00:06.231Z"
  },
  {
    "id": "the-open-network",
    "symbol": "ton",
    "name": "Toncoin",
    "image": "https://coin-images.coingecko.com/coins/images/17980/large/photo_2024-09-10_17.09.00.jpeg?1725963446",
    "current_price": 1.52,
    "market_cap": 3698429931,
    "market_cap_rank": 43,
    "fully_diluted_valuation": 7823193634,
    "total_volume": 62342446,
    "high_24h": 1.53,
    "low_24h": 1.5,
    "price_change_24h": 0.00350723,
    "price_change_percentage_24h": 0.23154,
    "market_cap_change_24h": 7669274,
    "market_cap_change_percentage_24h": 0.2078,
    "circulating_supply": 2435867346.596236,
    "total_supply": 5152527498.326248,
    "max_supply": null,
    "ath": 8.25,
    "ath_change_percentage": -81.59282,
    "ath_date": "2024-06-15T00:36:51.509Z",
    "atl": 0.519364,
    "atl_change_percentage": 192.52253,
    "atl_date": "2021-09-21T00:33:11.092Z",
    "roi": null,
    "last_updated": "2026-01-28T09:00:05.655Z"
  },
  {
    "id": "crypto-com-chain",
    "symbol": "cro",
    "name": "Cronos",
    "image": "https://coin-images.coingecko.com/coins/images/7310/large/cro_token_logo.png?1696507599",
    "current_price": 0.090832,
    "market_cap": 3617003229,
    "market_cap_rank": 44,
    "fully_diluted_valuation": 8934197208,
    "total_volume": 11970792,
    "high_24h": 0.091361,
    "low_24h": 0.089575,
    "price_change_24h": 0.0002552,
    "price_change_percentage_24h": 0.28175,
    "market_cap_change_24h": 9951552,
    "market_cap_change_percentage_24h": 0.27589,
    "circulating_supply": 39817084536.25258,
    "total_supply": 98350391999.61923,
    "max_supply": 100000000000.0,
    "ath": 0.965407,
    "ath_change_percentage": -90.58354,
    "ath_date": "2021-11-24T15:53:54.855Z",
    "atl": 0.0121196,
    "atl_change_percentage": 650.08442,
    "atl_date": "2019-02-08T00:00:00.000Z",
    "roi": null,
    "last_updated": "2026-01-28T09:00:02.601Z"
  },
  {
    "id": "rain",
    "symbol": "rain",
    "name": "Rain",
    "image": "https://coin-images.coingecko.com/coins/images/69134/large/Rain_logo_1_.png?1762952191",
    "current_price": 0.00970072,
    "market_cap": 3297321064,
    "market_cap_rank": 45,
    "fully_diluted_valuation": 11158148167,
    "total_volume": 37933789,
    "high_24h": 0.01021683,
    "low_24h": 0.00967083,
    "price_change_24h": -0.000468289479997941,
    "price_change_percentage_24h": -4.60506,
    "market_cap_change_24h": -158882539.17113256,
    "market_cap_change_percentage_24h": -4.59702,
    "circulating_supply": 339816170419.763,
    "total_supply": 1149939331288.351,
    "max_supply": 1150000000000.0,
    "ath": 0.01047029,
    "ath_change_percentage": -7.28417,
    "ath_date": "2026-01-26T21:45:56.203Z",
    "atl": 0.00222126,
    "atl_change_percentage": 337.03201,
    "atl_date": "2025-09-14T08:56:57.416Z",
    "roi": null,
    "last_updated": "2026-01-28T09:00:05.452Z"
  },
  {
    "id": "polkadot",
    "symbol": "dot",
    "name": "Polkadot",
    "image": "https://coin-images.coingecko.com/coins/images/12171/large/polkadot.jpg?1766533446",
    "current_price": 1.86,
    "market_cap": 3081401936,
    "market_cap_rank": 46,
    "fully_diluted_valuation": 3081401936,
    "total_volume": 118647415,
    "high_24h": 1.89,
    "low_24h": 1.83,
    "price_change_24h": -0.003577857609169399,
    "price_change_percentage_24h": -0.19234,
    "market_cap_change_24h": -5752805.686468124,
    "market_cap_change_percentage_24h": -0.18635,
    "circulating_supply": 1659674182.805782,
    "total_supply": 1659674182.805782,
    "max_supply": null,
    "ath": 54.98,
    "ath_change_percentage": -96.62013,
    "ath_date": "2021-11-04T14:10:09.301Z",
    "atl": 1.66,
    "atl_change_percentage": 12.16323,
    "atl_date": "2025-12-26T00:55:32.469Z",
    "roi": null,
    "last_updated": "2026-01-28T08:59:59.160Z"
  },
  {
    "id": "uniswap",
    "symbol": "uni",
    "name": "Uniswap",
    "image": "https://coin-images.coingecko.com/coins/images/12504/large/uniswap-logo.png?1720676669",
    "current_price": 4.79,
    "market_cap": 3036842502,
    "market_cap_rank": 47,
    "fully_diluted_valuation": 4305011316,
    "total_volume": 158054606,
    "high_24h": 4.81,
    "low_24h": 4.64,
    "price_change_24h": 0.104296,
    "price_change_percentage_24h": 2.22781,
    "market_cap_change_24h": 65552517,
    "market_cap_change_percentage_24h": 2.2062,
    "circulating_supply": 634551278.1684799,
    "total_supply": 899536420.0370889,
    "max_supply": 1000000000.0,
    "ath": 44.92,
    "ath_change_percentage": -89.32812,
    "ath_date": "2021-05-03T05:25:04.822Z",
    "atl": 1.03,
    "atl_change_percentage": 365.32092,
    "atl_date": "2020-09-17T01:20:38.214Z",
    "roi": null,
    "last_updated": "2026-01-28T08:59:57.546Z"
  },
  {
    "id": "mantle",
    "symbol": "mnt",
    "name": "Mantle",
    "image": "https://coin-images.coingecko.com/coins/images/30980/large/MNT_Token_Logo.png?1765516974",
    "current_price": 0.913687,
    "market_cap": 2972833608,
    "market_cap_rank": 48,
    "fully_diluted_valuation": 5683772506,
    "total_volume": 47753286,
    "high_24h": 0.914692,
    "low_24h": 0.865512,
    "price_change_24h": 0.04118629,
    "price_change_percentage_24h": 4.72049,
    "market_cap_change_24h": 134338544,
    "market_cap_change_percentage_24h": 4.73274,
    "circulating_supply": 3252944055.636841,
    "total_supply": 6219316794.89,
    "max_supply": 6219316794.89,
    "ath": 2.86,
    "ath_change_percentage": -68.50648,
    "ath_date": "2025-10-09T01:04:46.659Z",
    "atl": 0.307978,
    "atl_change_percentage": 191.95568,
    "atl_date": "2023-10-18T02:50:46.942Z",
    "roi": null,
    "last_updated": "2026-01-28T08:59:55.912Z"
  },
  {
    "id": "tether-gold",
    "symbol": "xaut",
    "name": "Tether Gold",
    "image": "https://coin-images.coingecko.com/coins/images/10481/large/Tether_Gold.png?1696510471",
    "current_price": 5295.91,
    "market_cap": 2754348413,
    "market_cap_rank": 49,
    "fully_diluted_valuation": 2754348413,
    "total_volume": 450608775,
    "high_24h": 5308.55,
    "low_24h": 5055.0,
    "price_change_24h": 221.04,
    "price_change_percentage_24h": 4.35548,
    "market_cap_change_24h": 114722120,
    "market_cap_change_percentage_24h": 4.34615,
    "circulating_supply": 520089.3,
    "total_supply": 520089.3,
    "max_supply": null,
    "ath": 5308.55,
    "ath_change_percentage": -0.00942,
    "ath_date": "2026-01-28T08:36:20.445Z",
    "atl": 1447.84,
    "atl_change_percentage": 266.61848,
    "atl_date": "2020-03-19T13:45:41.821Z",
    "roi": null,
    "last_updated": "2026-01-28T08:59:58.269Z"
  },
  {
    "id": "memecore",
    "symbol": "m",
    "name": "MemeCore",
    "image": "https://coin-images.coingecko.com/coins/images/53247/large/square-bg-transparent.png?1752637478",
    "current_price": 1.55,
    "market_cap": 2679085154,
    "market_cap_rank": 50,
    "fully_diluted_valuation": 8256447846,
    "total_volume": 8678496,
    "high_24h": 1.59,
    "low_24h": 1.52,
    "price_change_24h": -0.013084739605641715,
    "price_change_percentage_24h": -0.8375,
    "market_cap_change_24h": -22113383.074408054,
    "market_cap_change_percentage_24h": -0.81865,
    "circulating_supply": 1729259344.40651,
    "total_supply": 5329259343.965786,
    "max_supply": 10000000000.0,
    "ath": 2.96,
    "ath_change_percentage": -47.5932,
    "ath_date": "2025-09-18T07:27:06.144Z",
    "atl": 0.04746135,
    "atl_change_percentage": 3167.07587,
    "atl_date": "2025-07-04T03:56:17.448Z",
    "roi": null,
    "last_updated": "2026-01-28T09:00:02.773Z"
  },
  {
    "id": "bitget-token",
    "symbol": "bgb",
    "name": "Bitget Token",
    "image": "https://coin-images.coingecko.com/coins/images/11610/large/Bitget_logo.png?1736925727",
    "current_price": 3.58,
    "market_cap": 2508096707,
    "market_cap_rank": 51,
    "fully_diluted_valuation": 3285399027,
    "total_volume": 27605091,
    "high_24h": 3.59,
    "low_24h": 3.56,
    "price_change_24h": -0.007783451702101374,
    "price_change_percentage_24h": -0.21676,
    "market_cap_change_24h": -5450233.730929375,
    "market_cap_change_percentage_24h": -0.21683,
    "circulating_supply": 699992035.9787906,
    "total_supply": 916931610.9787906,
    "max_supply": 2000000000.0,
    "ath": 8.45,
    "ath_change_percentage": -57.60325,
    "ath_date": "2024-12-27T11:41:24.992Z",
    "atl": 0.0142795,
    "atl_change_percentage": 24989.55082,
    "atl_date": "2020-06-25T04:17:05.895Z",
    "roi": null,
    "last_updated": "2026-01-28T09:00:12.041Z"
  },
  {
    "id": "aave",
    "symbol": "aave",
    "name": "Aave",
    "image": "https://coin-images.coingecko.com/coins/images/12645/large/aave-token-round.png?1720472354",
    "current_price": 157.97,
    "market_cap": 2399074937,
    "market_cap_rank": 52,
    "fully_diluted_valuation": 2527901901,
    "total_volume": 395943848,
    "high_24h": 159.43,
    "low_24h": 153.09,
    "price_change_24h": 3.41,
    "price_change_percentage_24h": 2.20828,
    "market_cap_change_24h": 52009993,
    "market_cap_change_percentage_24h": 2.21596,
    "circulating_supply": 15184607.826415818,
    "total_supply": 16000000.0,
    "max_supply": 16000000.0,
    "ath": 661.69,
    "ath_change_percentage": -76.07556,
    "ath_date": "2021-05-18T21:19:59.514Z",
    "atl": 26.02,
    "atl_change_percentage": 508.32615,
    "atl_date": "2020-11-05T09:20:11.928Z",
    "roi": null,
    "last_updated": "2026-01-28T09:00:11.635Z"
  },
  {
    "id": "bittensor",
    "symbol": "tao",
    "name": "Bittensor",
    "image": "https://coin-images.coingecko.com/coins/images/28452/large/ARUsPeNQ_400x400.jpeg?1696527447",
    "current_price": 236.38,
    "market_cap": 2268891235,
    "market_cap_rank": 53,
    "fully_diluted_valuation": 4964497069,
    "total_volume": 65188832,
    "high_24h": 238.73,
    "low_24h": 228.69,
    "price_change_24h": 4.4,
    "price_change_percentage_24h": 1.89576,
    "market_cap_change_24h": 42456668,
    "market_cap_change_percentage_24h": 1.90694,
    "circulating_supply": 9597491.0,
    "total_supply": 21000000.0,
    "max_supply": 21000000.0,
    "ath": 757.6,
    "ath_change_percentage": -68.72056,
    "ath_date": "2024-03-07T18:45:36.466Z",
    "atl": 30.83,
    "atl_change_percentage": 668.65003,
    "atl_date": "2023-05-14T08:57:53.732Z",
    "roi": null,
    "last_updated": "2026-01-28T09:00:12.357Z"
  },
  {
    "id": "okb",
    "symbol": "okb",
    "name": "OKB",
    "image": "https://coin-images.coingecko.com/coins/images/4463/large/WeChat_Image_20220118095654.png?1696505053",
    "current_price": 106.64,
    "market_cap": 2239461382,
    "market_cap_rank": 54,
    "fully_diluted_valuation": 2239461382,
    "total_volume": 20449122,
    "high_24h": 107.72,
    "low_24h": 103.68,
    "price_change_24h": 2.61,
    "price_change_percentage_24h": 2.51027,
    "market_cap_change_24h": 54723899,
    "market_cap_change_percentage_24h": 2.50483,
    "circulating_supply": 21000000.0,
    "total_supply": 21000000.0,
    "max_supply": 21000000.0,
    "ath": 255.5,
    "ath_change_percentage": -58.26229,
    "ath_date": "2025-08-22T01:50:26.131Z",
    "atl": 0.580608,
    "atl_change_percentage": 18267.09489,
    "atl_date": "2019-01-14T00:00:00.000Z",
    "roi": null,
    "last_updated": "2026-01-28T09:00:03.214Z"
  },
  {
    "id": "pax-gold",
    "symbol": "paxg",
    "name": "PAX Gold",
    "image": "https://coin-images.coingecko.com/coins/images/9519/large/paxgold.png?1696509604",
    "current_price": 5309.99,
    "market_cap": 2210431456,
    "market_cap_rank": 55,
    "fully_diluted_valuation": 2210431456,
    "total_volume": 7803363793,
    "high_24h": 5321.54,
    "low_24h": 5063.62,
    "price_change_24h": 216.29,
    "price_change_percentage_24h": 4.24612,
    "market_cap_change_24h": 139852008,
    "market_cap_change_percentage_24h": 6.75424,
    "circulating_supply": 416283.205,
    "total_supply": 416283.205,
    "max_supply": null,
    "ath": 5308.72,
    "ath_change_percentage": 0.24139,
    "ath_date": "2026-01-28T08:16:29.013Z",
    "atl": 1399.64,
    "atl_change_percentage": 280.2071,
    "atl_date": "2019-11-18T03:09:35.959Z",
    "roi": null,
    "last_updated": "2026-01-28T09:00:09.963Z"
  },
  {
    "id": "falcon-finance",
    "symbol": "usdf",
    "name": "Falcon USD",
    "image": "https://coin-images.coingecko.com/coins/images/54558/large/ff_200_X_200.png?1740741076",
    "current_price": 0.995483,
    "market_cap": 2167399693,
    "market_cap_rank": 56,
    "fully_diluted_valuation": 2167399693,
    "total_volume": 2293742,
    "high_24h": 0.997195,
    "low_24h": 0.992047,
    "price_change_24h": -0.000409263583366681,
    "price_change_percentage_24h": -0.0411,
    "market_cap_change_24h": -2148626.842795372,
    "market_cap_change_percentage_24h": -0.09904,
    "circulating_supply": 2178870591.992906,
    "total_supply": 2178870591.992906,
    "max_supply": null,
    "ath": 1.075,
    "ath_change_percentage": -7.37039,
    "ath_date": "2025-05-08T21:25:42.071Z",
    "atl": 0.943422,
    "atl_change_percentage": 5.50751,
    "atl_date": "2025-07-08T10:16:34.749Z",
    "roi": null,
    "last_updated": "2026-01-28T09:00:06.273Z"
  },
  {
    "id": "pepe",
    "symbol": "pepe",
    "name": "Pepe",
    "image": "https://coin-images.coingecko.com/coins/images/29850/large/pepe-token.jpeg?1696528776",
    "current_price": 5.01e-06,
    "market_cap": 2108058062,
    "market_cap_rank": 57,
    "fully_diluted_valuation": 2108058062,
    "total_volume": 365918815,
    "high_24h": 5.09e-06,
    "low_24h": 4.86e-06,
    "price_change_24h": 1.3928e-08,
    "price_change_percentage_24h": 0.27875,
    "market_cap_change_24h": 5744697,
    "market_cap_change_percentage_24h": 0.27326,
    "circulating_supply": 420690000000000.0,
    "total_supply": 420690000000000.0,
    "max_supply": 420690000000000.0,
    "ath": 2.803e-05,
    "ath_change_percentage": -82.12344,
    "ath_date": "2024-12-09T16:30:35.828Z",
    "atl": 5.5142e-08,
    "atl_change_percentage": 8986.43282,
    "atl_date": "2023-04-18T02:14:41.591Z",
    "roi": null,
    "last_updated": "2026-01-28T09:00:10.051Z"
  },
  {
    "id": "pump-fun",
    "symbol": "pump",
    "name": "Pump.fun",
    "image": "https://coin-images.coingecko.com/coins/images/67164/large/pump.jpg?1751949376",
    "current_price": 0.00327519,
    "market_cap": 1935336987,
    "market_cap_rank": 58,
    "fully_diluted_valuation": 3280196807,
    "total_volume": 248046064,
    "high_24h": 0.00328938,
    "low_24h": 0.00303103,
    "price_change_24h": 0.00019126,
    "price_change_percentage_24h": 6.20195,
    "market_cap_change_24h": 112954822,
    "market_cap_change_percentage_24h": 6.1982,
    "circulating_supply": 590000000000.0,
    "total_supply": 999989215697.2119,
    "max_supply": 1000000000000.0,
    "ath": 0.00881908,
    "ath_change_percentage": -62.86243,
    "ath_date": "2025-09-14T16:42:40.248Z",
    "atl": 0.00168627,
    "atl_change_percentage": 94.22707,
    "atl_date": "2025-12-24T03:14:28.269Z",
    "roi": null,
    "last_updated": "2026-01-28T09:00:10.207Z"
  },
  {
    "id": "near",
    "symbol": "near",
    "name": "NEAR Protocol",
    "image": "https://coin-images.coingecko.com/coins/images/10365/large/near.jpg?1696510367",
    "current_price": 1.47,
    "market_cap": 1886470881,
    "market_cap_rank": 59,
    "fully_diluted_valuation": 1886470928,
    "total_volume": 102161664,
    "high_24h": 1.5,
    "low_24h": 1.45,
    "price_change_24h": 0.00042535,
    "price_change_percentage_24h": 0.029,
    "market_cap_change_24h": 290958,
    "market_cap_change_percentage_24h": 0.01543,
    "circulating_supply": 1286284587.0,
    "total_supply": 1286284619.0,
    "max_supply": null,
    "ath": 20.44,
    "ath_change_percentage": -92.82631,
    "ath_date": "2022-01-16T22:09:45.873Z",
    "atl": 0.526762,
    "atl_change_percentage": 178.33553,
    "atl_date": "2020-11-04T16:09:15.137Z",
    "roi": null,
    "last_updated": "2026-01-28T09:00:05.156Z"
  },
  {
    "id": "jito-staked-sol",
    "symbol": "jitosol",
    "name": "Jito Staked SOL",
    "image": "https://coin-images.coingecko.com/coins/images/28046/large/JitoSOL-200.png?1696527060",
    "current_price": 159.12,
    "market_cap": 1813911965,
    "market_cap_rank": 60,
    "fully_diluted_valuation": 1813911965,
    "total_volume": 12356538,
    "high_24h": 160.33,
    "low_24h": 154.73,
    "price_change_24h": 3.42,
    "price_change_percentage_24h": 2.19388,
    "market_cap_change_24h": 28240417,
    "market_cap_change_percentage_24h": 1.5815,
    "circulating_supply": 11399215.38687841,
    "total_supply": 11399215.38687841,
    "max_supply": null,
    "ath": 339.52,
    "ath_change_percentage": -53.08642,
    "ath_date": "2025-01-19T11:21:54.080Z",
    "atl": 0.57898,
    "atl_change_percentage": 27410.67006,
    "atl_date": "2023-09-12T10:21:17.665Z",
    "roi": null,
    "last_updated": "2026-01-28T09:00:02.690Z"
  },
  {
    "id": "binance-peg-weth",
    "symbol": "weth",
    "name": "Binance-Peg WETH",
    "image": "https://coin-images.coingecko.com/coins/images/39580/large/weth.png?1723006716",
    "current_price": 2993.85,
    "market_cap": 1811353412,
    "market_cap_rank": 61,
    "fully_diluted_valuation": 1811353412,
    "total_volume": 45809910,
    "high_24h": 3030.51,
    "low_24h": 2898.82,
    "price_change_24h": 75.48,
    "price_change_percentage_24h": 2.58644,
    "market_cap_change_24h": 45180763,
    "market_cap_change_percentage_24h": 2.55812,
    "circulating_supply": 604999.9999588211,
    "total_supply": 604999.9999588211,
    "max_supply": null,
    "ath": 4955.78,
    "ath_change_percentage": -39.67384,
    "ath_date": "2025-08-24T19:14:00.505Z",
    "atl": 1394.32,
    "atl_change_percentage": 114.4153,
    "atl_date": "2025-04-09T01:32:41.942Z",
    "roi": null,
    "last_updated": "2026-01-28T09:00:12.573Z"
  },
  {
    "id": "kelp-dao-restaked-eth",
    "symbol": "rseth",
    "name": "Kelp DAO Restaked ETH",
    "image": "https://coin-images.coingecko.com/coins/images/33800/large/Icon___Dark.png?1702991855",
    "current_price": 3192.99,
    "market_cap": 1804981183,
    "market_cap_rank": 62,
    "fully_diluted_valuation": 1804981183,
    "total_volume": 694079,
    "high_24h": 3220.13,
    "low_24h": 3081.13,
    "price_change_24h": 88.68,
    "price_change_percentage_24h": 2.85672,
    "market_cap_change_24h": 132543901,
    "market_cap_change_percentage_24h": 7.92519,
    "circulating_supply": 565338.4344728999,
    "total_supply": 565338.4344728999,
    "max_supply": null,
    "ath": 5190.42,
    "ath_change_percentage": -38.45617,
    "ath_date": "2025-08-24T19:13:49.359Z",
    "atl": 1029.61,
    "atl_change_percentage": 210.2524,
    "atl_date": "2025-09-02T07:53:14.684Z",
    "roi": null,
    "last_updated": "2026-01-28T09:00:06.581Z"
  },
  {
    "id": "ethereum-classic",
    "symbol": "etc",
    "name": "Ethereum Classic",
    "image": "https://coin-images.coingecko.com/coins/images/453/large/ethereum-classic-logo.png?1696501717",
    "current_price": 11.5,
    "market_cap": 1786216246,
    "market_cap_rank": 63,
    "fully_diluted_valuation": 1786293820,
    "total_volume": 50009129,
    "high_24h": 11.59,
    "low_24h": 11.22,
    "price_change_24h": 0.217138,
    "price_change_percentage_24h": 1.92414,
    "market_cap_change_24h": 33585274,
    "market_cap_change_percentage_24h": 1.91628,
    "circulating_supply": 155295024.1078442,
    "total_supply": 155301768.4001304,
    "max_supply": 210700000.0,
    "ath": 167.09,
    "ath_change_percentage": -93.1,
    "ath_date": "2021-05-06T18:34:22.133Z",
    "atl": 0.615038,
    "atl_change_percentage": 1774.50021,
    "atl_date": "2016-07-25T00:00:00.000Z",
    "roi": {
      "times": 24.560132601495024,
      "currency": "usd",
      "percentage": 2456.013260149502
    },
    "last_updated": "2026-01-28T09:00:05.285Z"
  },
  {
    "id": "internet-computer",
    "symbol": "icp",
    "name": "Internet Computer",
    "image": "https://coin-images.coingecko.com/coins/images/14495/large/Internet_Computer_logo.png?1696514180",
    "current_price": 3.26,
    "market_cap": 1783003554,
    "market_cap_rank": 64,
    "fully_diluted_valuation": 1783003554,
    "total_volume": 72090734,
    "high_24h": 3.37,
    "low_24h": 3.22,
    "price_change_24h": -0.02247491291665593,
    "price_change_percentage_24h": -0.68556,
    "market_cap_change_24h": -13326415.870023489,
    "market_cap_change_percentage_24h": -0.74187,
    "circulating_supply": 547606758.1160514,
    "total_supply": 547606758.1160514,
    "max_supply": null,
    "ath": 700.65,
    "ath_change_percentage": -99.53567,
    "ath_date": "2021-05-10T16:05:53.653Z",
    "atl": 2.23,
    "atl_change_percentage": 45.78469,
    "atl_date": "2025-10-10T21:26:36.019Z",
    "roi": null,
    "last_updated": "2026-01-28T09:00:06.779Z"
  },
  {
    "id": "aster-2",
    "symbol": "aster",
    "name": "Aster",
    "image": "https://coin-images.coingecko.com/coins/images/69040/large/_ASTER.png?1757326782",
    "current_price": 0.688615,
    "market_cap": 1693206887,
    "market_cap_rank": 65,
    "fully_diluted_valuation": 5467353167,
    "total_volume": 134734654,
    "high_24h": 0.705878,
    "low_24h": 0.636965,
    "price_change_24h": 0.02701684,
    "price_change_percentage_24h": 4.08357,
    "market_cap_change_24h": 69480574,
    "market_cap_change_percentage_24h": 4.27908,
    "circulating_supply": 2453439672.0,
    "total_supply": 7922139499.822846,
    "max_supply": 8000000000.0,
    "ath": 2.41,
    "ath_change_percentage": -71.41178,
    "ath_date": "2025-09-24T11:18:14.634Z",
    "atl": 0.099713,
    "atl_change_percentage": 590.59358,
    "atl_date": "2025-09-17T12:05:36.771Z",
    "roi": null,
    "last_updated": "2026-01-28T09:00:09.495Z"
  },
  {
    "id": "blackrock-usd-institutional-digital-liquidity-fund",
    "symbol": "buidl",
    "name": "BlackRock USD Institutional Digital Liquidity Fund",
    "image": "https://coin-images.coingecko.com/coins/images/36291/large/blackrock.png?1711013223",
    "current_price": 1.0,
    "market_cap": 1685400913,
    "market_cap_rank": 66,
    "fully_diluted_valuation": 1685400913,
    "total_volume": 0.0,
    "high_24h": 1.0,
    "low_24h": 1.0,
    "price_change_24h": 0.0,
    "price_change_percentage_24h": 0.0,
    "market_cap_change_24h": 161444,
    "market_cap_change_percentage_24h": 0.00958,
    "circulating_supply": 1685400912.820449,
    "total_supply": 1685400912.820449,
    "max_supply": null,
    "ath": 1.0,
    "ath_change_percentage": 0.0,
    "ath_date": "2025-02-12T05:00:10.912Z",
    "atl": 1.0,
    "atl_change_percentage": 0.0,
    "atl_date": "2025-02-12T05:45:10.196Z",
    "roi": null,
    "last_updated": "2026-01-28T08:55:05.226Z"
  },
  {
    "id": "ondo-finance",
    "symbol": "ondo",
    "name": "Ondo",
    "image": "https://coin-images.coingecko.com/coins/images/26580/large/ONDO.png?1696525656",
    "current_price": 0.339418,
    "market_cap": 1652794371,
    "market_cap_rank": 67,
    "fully_diluted_valuation": 3394294804,
    "total_volume": 54481098,
    "high_24h": 0.341162,
    "low_24h": 0.323838,
    "price_change_24h": 0.00591485,
    "price_change_percentage_24h": 1.77355,
    "market_cap_change_24h": 27881628,
    "market_cap_change_percentage_24h": 1.71588,
    "circulating_supply": 4869330647.0,
    "total_supply": 10000000000.0,
    "max_supply": 10000000000.0,
    "ath": 2.14,
    "ath_change_percentage": -84.14049,
    "ath_date": "2024-12-16T00:36:00.777Z",
    "atl": 0.082171,
    "atl_change_percentage": 313.06346,
    "atl_date": "2024-01-18T12:14:30.524Z",
    "roi": null,
    "last_updated": "2026-01-28T09:00:05.289Z"
  },
  {
    "id": "hashnote-usyc",
    "symbol": "usyc",
    "name": "Circle USYC",
    "image": "https://coin-images.coingecko.com/coins/images/51054/large/Hashnote_SDYC_200x200.png?1730370965",
    "current_price": 1.11,
    "market_cap": 1608230246,
    "market_cap_rank": 68,
    "fully_diluted_valuation": 1681132188,
    "total_volume": 1334.85,
    "high_24h": null,
    "low_24h": null,
    "price_change_24h": null,
    "price_change_percentage_24h": null,
    "market_cap_change_24h": null,
    "market_cap_change_percentage_24h": null,
    "circulating_supply": 1511302682.577064,
    "total_supply": 1511302682.577064,
    "max_supply": null,
    "ath": 1.12,
    "ath_change_percentage": -0.39829,
    "ath_date": "2025-03-04T19:26:50.778Z",
    "atl": 1.026,
    "atl_change_percentage": 8.40755,
    "atl_date": "2024-12-05T22:31:20.475Z",
    "roi": null,
    "last_updated": "2026-01-16T07:20:42.577Z"
  },
  {
    "id": "htx-dao",
    "symbol": "htx",
    "name": "HTX DAO",
    "image": "https://coin-images.coingecko.com/coins/images/35491/large/Frame_1321318576.png?1708908626",
    "current_price": 1.75e-06,
    "market_cap": 1604701971,
    "market_cap_rank": 69,
    "fully_diluted_valuation": 1604701971,
    "total_volume": 74747992,
    "high_24h": 1.78e-06,
    "low_24h": 1.74e-06,
    "price_change_24h": -3.0523691571e-08,
    "price_change_percentage_24h": -1.7135,
    "market_cap_change_24h": -27235492.52573347,
    "market_cap_change_percentage_24h": -1.66891,
    "circulating_supply": 916533066327098.8,
    "total_supply": 916533066327098.8,
    "max_supply": 999990000000000.0,
    "ath": 3.75e-06,
    "ath_change_percentage": -53.28226,
    "ath_date": "2024-12-04T00:16:20.770Z",
    "atl": 8.00816e-07,
    "atl_change_percentage": 118.85355,
    "atl_date": "2024-08-05T13:31:33.427Z",
    "roi": null,
    "last_updated": "2026-01-28T09:00:02.319Z"
  },
  {
    "id": "global-dollar",
    "symbol": "usdg",
    "name": "Global Dollar",
    "image": "https://coin-images.coingecko.com/coins/images/51281/large/GDN_USDG_Token_200x200.png?1730484111",
    "current_price": 0.99968,
    "market_cap": 1582695514,
    "market_cap_rank": 70,
    "fully_diluted_valuation": 1582695514,
    "total_volume": 29767168,
    "high_24h": 0.999807,
    "low_24h": 0.999357,
    "price_change_24h": 6.181e-05,
    "price_change_percentage_24h": 0.00618,
    "market_cap_change_24h": -11017729.122314453,
    "market_cap_change_percentage_24h": -0.69132,
    "circulating_supply": 1583315955.717424,
    "total_supply": 1583315955.717424,
    "max_supply": null,
    "ath": 1.65,
    "ath_change_percentage": -39.58404,
    "ath_date": "2025-01-30T00:11:05.728Z",
    "atl": 0.907561,
    "atl_change_percentage": 10.14041,
    "atl_date": "2024-11-11T23:55:50.604Z",
    "roi": null,
    "last_updated": "2026-01-28T09:00:02.863Z"
  },
  {
    "id": "wrapped-solana",
    "symbol": "sol",
    "name": "Wrapped SOL",
    "image": "https://coin-images.coingecko.com/coins/images/21629/large/solana.jpg?1696520989",
    "current_price": 126.53,
    "market_cap": 1563799947,
    "market_cap_rank": 71,
    "fully_diluted_valuation": 1563799947,
    "total_volume": 1813768359,
    "high_24h": 127.62,
    "low_24h": 123.03,
    "price_change_24h": 2.6,
    "price_change_percentage_24h": 2.09907,
    "market_cap_change_24h": 5947437,
    "market_cap_change_percentage_24h": 0.38177,
    "circulating_supply": 12352733.2418358,
    "total_supply": 12352733.2418358,
    "max_supply": null,
    "ath": 290.3,
    "ath_change_percentage": -56.36427,
    "ath_date": "2025-01-19T11:20:39.814Z",
    "atl": 8.11,
    "atl_change_percentage": 1461.85231,
    "atl_date": "2022-12-29T20:45:41.226Z",
    "roi": null,
    "last_updated": "2026-01-28T09:00:11.893Z"
  },
  {
    "id": "jupiter-perpetuals-liquidity-provider-token",
    "symbol": "jlp",
    "name": "Jupiter Perpetuals Liquidity Provider Token",
    "image": "https://coin-images.coingecko.com/coins/images/33094/large/jlp.png?1700631386",
    "current_price": 4.6,
    "market_cap": 1563103236,
    "market_cap_rank": 72,
    "fully_diluted_valuation": 1563103236,
    "total_volume": 29148858,
    "high_24h": 4.62,
    "low_24h": 4.53,
    "price_change_24h": 0.055331,
    "price_change_percentage_24h": 1.21725,
    "market_cap_change_24h": 25490074,
    "market_cap_change_percentage_24h": 1.65777,
    "circulating_supply": 339721381.243003,
    "total_supply": 339721381.243003,
    "max_supply": null,
    "ath": 5.99,
    "ath_change_percentage": -23.1068,
    "ath_date": "2025-10-06T17:35:59.480Z",
    "atl": 0.146839,
    "atl_change_percentage": 3035.4179,
    "atl_date": "2023-11-24T05:55:06.706Z",
    "roi": null,
    "last_updated": "2026-01-28T09:00:06.720Z"
  },
  {
    "id": "sky",
    "symbol": "sky",
    "name": "Sky",
    "image": "https://coin-images.coingecko.com/coins/images/39925/large/sky.jpg?1724827980",
    "current_price": 0.065023,
    "market_cap": 1495368692,
    "market_cap_rank": 73,
    "fully_diluted_valuation": 1525657614,
    "total_volume": 10567903,
    "high_24h": 0.065102,
    "low_24h": 0.062756,
    "price_change_24h": 0.00201813,
    "price_change_percentage_24h": 3.20316,
    "market_cap_change_24h": 45992163,
    "market_cap_change_percentage_24h": 3.17324,
    "circulating_supply": 22996860228.614304,
    "total_supply": 23462665147.36596,
    "max_supply": 23462665147.3,
    "ath": 0.100535,
    "ath_change_percentage": -35.244,
    "ath_date": "2024-12-04T10:13:57.264Z",
    "atl": 0.03582727,
    "atl_change_percentage": 81.71241,
    "atl_date": "2025-02-03T05:01:48.626Z",
    "roi": null,
    "last_updated": "2026-01-28T09:00:10.282Z"
  },
  {
    "id": "pi-network",
    "symbol": "pi",
    "name": "Pi Network",
    "image": "https://coin-images.coingecko.com/coins/images/54342/large/pi_network.jpg?1739347576",
    "current_price": 0.17285,
    "market_cap": 1451560101,
    "market_cap_rank": 74,
    "fully_diluted_valuation": 2233169386,
    "total_volume": 11067281,
    "high_24h": 0.176069,
    "low_24h": 0.171379,
    "price_change_24h": 0.00022682,
    "price_change_percentage_24h": 0.13139,
    "market_cap_change_24h": 4419554,
    "market_cap_change_percentage_24h": 0.3054,
    "circulating_supply": 8390103227.476212,
    "total_supply": 12907851119.19417,
    "max_supply": 100000000000.0,
    "ath": 2.99,
    "ath_change_percentage": -94.20121,
    "ath_date": "2025-02-26T16:41:03.732Z",
    "atl": 0.168713,
    "atl_change_percentage": 2.68633,
    "atl_date": "2026-01-26T20:31:57.508Z",
    "roi": null,
    "last_updated": "2026-01-28T09:00:05.295Z"
  },
  {
    "id": "kucoin-shares",
    "symbol": "kcs",
    "name": "KuCoin",
    "image": "https://coin-images.coingecko.com/coins/images/1047/large/sa9z79.png?1696502152",
    "current_price": 10.9,
    "market_cap": 1441180025,
    "market_cap_rank": 75,
    "fully_diluted_valuation": 1550232258,
    "total_volume": 2071282,
    "high_24h": 10.96,
    "low_24h": 10.59,
    "price_change_24h": 0.176092,
    "price_change_percentage_24h": 1.64266,
    "market_cap_change_24h": 23845695,
    "market_cap_change_percentage_24h": 1.68243,
    "circulating_supply": 132155021.7355671,
    "total_supply": 142155021.7355671,
    "max_supply": null,
    "ath": 28.83,
    "ath_change_percentage": -62.16235,
    "ath_date": "2021-12-01T15:09:35.541Z",
    "atl": 0.342863,
    "atl_change_percentage": 3081.60585,
    "atl_date": "2019-02-07T00:00:00.000Z",
    "roi": null,
    "last_updated": "2026-01-28T09:00:06.806Z"
  }
]